[
  {
    "ContainingType": "ApiEjemplo.Controllers.CatacionsController",
    "Method": "GetCataciones",
    "RelativePath": "api/Catacions",
    "HttpMethod": "GET",
    "IsController": true,
    "Order": 0,
    "Parameters": [],
    "ReturnTypes": [
      {
        "Type": "System.Collections.Generic.IEnumerable\u00601[[ApiEjemplo.Models.Catacion, ApiEjemplo, Version=1.0.0.0, Culture=neutral, PublicKeyToken=null]]",
        "MediaTypes": [
          "text/plain",
          "application/json",
          "text/json"
        ],
        "StatusCode": 200
      }
    ]
  },
  {
    "ContainingType": "ApiEjemplo.Controllers.CatacionsController",
    "Method": "PostCatacion",
    "RelativePath": "api/Catacions",
    "HttpMethod": "POST",
    "IsController": true,
    "Order": 0,
    "Parameters": [
      {
        "Name": "catacion",
        "Type": "ApiEjemplo.Models.Catacion",
        "IsRequired": true
      }
    ],
    "ReturnTypes": [
      {
        "Type": "ApiEjemplo.Models.Catacion",
        "MediaTypes": [
          "text/plain",
          "application/json",
          "text/json"
        ],
        "StatusCode": 200
      }
    ]
  },
  {
    "ContainingType": "ApiEjemplo.Controllers.CatacionsController",
    "Method": "GetCatacion",
    "RelativePath": "api/Catacions/{id}",
    "HttpMethod": "GET",
    "IsController": true,
    "Order": 0,
    "Parameters": [
      {
        "Name": "id",
        "Type": "System.Int32",
        "IsRequired": true
      }
    ],
    "ReturnTypes": [
      {
        "Type": "ApiEjemplo.Models.Catacion",
        "MediaTypes": [
          "text/plain",
          "application/json",
          "text/json"
        ],
        "StatusCode": 200
      }
    ]
  },
  {
    "ContainingType": "ApiEjemplo.Controllers.CatacionsController",
    "Method": "PutCatacion",
    "RelativePath": "api/Catacions/{id}",
    "HttpMethod": "PUT",
    "IsController": true,
    "Order": 0,
    "Parameters": [
      {
        "Name": "id",
        "Type": "System.Int32",
        "IsRequired": true
      },
      {
        "Name": "catacion",
        "Type": "ApiEjemplo.Models.Catacion",
        "IsRequired": true
      }
    ],
    "ReturnTypes": []
  },
  {
    "ContainingType": "ApiEjemplo.Controllers.CatacionsController",
    "Method": "DeleteCatacion",
    "RelativePath": "api/Catacions/{id}",
    "HttpMethod": "DELETE",
    "IsController": true,
    "Order": 0,
    "Parameters": [
      {
        "Name": "id",
        "Type": "System.Int32",
        "IsRequired": true
      }
    ],
    "ReturnTypes": []
  },
  {
    "ContainingType": "ApiEjemplo.Controllers.ClientesController",
    "Method": "GetClientes",
    "RelativePath": "api/Clientes",
    "HttpMethod": "GET",
    "IsController": true,
    "Order": 0,
    "Parameters": [],
    "ReturnTypes": [
      {
        "Type": "System.Collections.Generic.IEnumerable\u00601[[ApiEjemplo.Models.Clientes, ApiEjemplo, Version=1.0.0.0, Culture=neutral, PublicKeyToken=null]]",
        "MediaTypes": [
          "text/plain",
          "application/json",
          "text/json"
        ],
        "StatusCode": 200
      }
    ]
  },
  {
    "ContainingType": "ApiEjemplo.Controllers.ClientesController",
    "Method": "PostClientes",
    "RelativePath": "api/Clientes",
    "HttpMethod": "POST",
    "IsController": true,
    "Order": 0,
    "Parameters": [
      {
        "Name": "clientes",
        "Type": "ApiEjemplo.Models.Clientes",
        "IsRequired": true
      }
    ],
    "ReturnTypes": [
      {
        "Type": "ApiEjemplo.Models.Clientes",
        "MediaTypes": [
          "text/plain",
          "application/json",
          "text/json"
        ],
        "StatusCode": 200
      }
    ]
  },
  {
    "ContainingType": "ApiEjemplo.Controllers.ClientesController",
    "Method": "GetClientes",
    "RelativePath": "api/Clientes/{id}",
    "HttpMethod": "GET",
    "IsController": true,
    "Order": 0,
    "Parameters": [
      {
        "Name": "id",
        "Type": "System.Int32",
        "IsRequired": true
      }
    ],
    "ReturnTypes": [
      {
        "Type": "ApiEjemplo.Models.Clientes",
        "MediaTypes": [
          "text/plain",
          "application/json",
          "text/json"
        ],
        "StatusCode": 200
      }
    ]
  },
  {
    "ContainingType": "ApiEjemplo.Controllers.ClientesController",
    "Method": "PutClientes",
    "RelativePath": "api/Clientes/{id}",
    "HttpMethod": "PUT",
    "IsController": true,
    "Order": 0,
    "Parameters": [
      {
        "Name": "id",
        "Type": "System.Int32",
        "IsRequired": true
      },
      {
        "Name": "clientes",
        "Type": "ApiEjemplo.Models.Clientes",
        "IsRequired": true
      }
    ],
    "ReturnTypes": []
  },
  {
    "ContainingType": "ApiEjemplo.Controllers.ClientesController",
    "Method": "DeleteClientes",
    "RelativePath": "api/Clientes/{id}",
    "HttpMethod": "DELETE",
    "IsController": true,
    "Order": 0,
    "Parameters": [
      {
        "Name": "id",
        "Type": "System.Int32",
        "IsRequired": true
      }
    ],
    "ReturnTypes": []
  },
  {
    "ContainingType": "ApiEjemplo.Controllers.EtapasController",
    "Method": "GetEtapas",
    "RelativePath": "api/Etapas",
    "HttpMethod": "GET",
    "IsController": true,
    "Order": 0,
    "Parameters": [],
    "ReturnTypes": [
      {
        "Type": "System.Collections.Generic.IEnumerable\u00601[[ApiEjemplo.Models.Etapas, ApiEjemplo, Version=1.0.0.0, Culture=neutral, PublicKeyToken=null]]",
        "MediaTypes": [
          "text/plain",
          "application/json",
          "text/json"
        ],
        "StatusCode": 200
      }
    ]
  },
  {
    "ContainingType": "ApiEjemplo.Controllers.EtapasController",
    "Method": "PostEtapas",
    "RelativePath": "api/Etapas",
    "HttpMethod": "POST",
    "IsController": true,
    "Order": 0,
    "Parameters": [
      {
        "Name": "etapas",
        "Type": "ApiEjemplo.Models.Etapas",
        "IsRequired": true
      }
    ],
    "ReturnTypes": [
      {
        "Type": "ApiEjemplo.Models.Etapas",
        "MediaTypes": [
          "text/plain",
          "application/json",
          "text/json"
        ],
        "StatusCode": 200
      }
    ]
  },
  {
    "ContainingType": "ApiEjemplo.Controllers.EtapasController",
    "Method": "GetEtapas",
    "RelativePath": "api/Etapas/{id}",
    "HttpMethod": "GET",
    "IsController": true,
    "Order": 0,
    "Parameters": [
      {
        "Name": "id",
        "Type": "System.Int32",
        "IsRequired": true
      }
    ],
    "ReturnTypes": [
      {
        "Type": "ApiEjemplo.Models.Etapas",
        "MediaTypes": [
          "text/plain",
          "application/json",
          "text/json"
        ],
        "StatusCode": 200
      }
    ]
  },
  {
    "ContainingType": "ApiEjemplo.Controllers.EtapasController",
    "Method": "PutEtapas",
    "RelativePath": "api/Etapas/{id}",
    "HttpMethod": "PUT",
    "IsController": true,
    "Order": 0,
    "Parameters": [
      {
        "Name": "id",
        "Type": "System.Int32",
        "IsRequired": true
      },
      {
        "Name": "etapas",
        "Type": "ApiEjemplo.Models.Etapas",
        "IsRequired": true
      }
    ],
    "ReturnTypes": []
  },
  {
    "ContainingType": "ApiEjemplo.Controllers.EtapasController",
    "Method": "DeleteEtapas",
    "RelativePath": "api/Etapas/{id}",
    "HttpMethod": "DELETE",
    "IsController": true,
    "Order": 0,
    "Parameters": [
      {
        "Name": "id",
        "Type": "System.Int32",
        "IsRequired": true
      }
    ],
    "ReturnTypes": []
  },
  {
    "ContainingType": "ApiEjemplo.Controllers.LoteEtapasController",
    "Method": "GetLoteEtapas",
    "RelativePath": "api/LoteEtapas",
    "HttpMethod": "GET",
    "IsController": true,
    "Order": 0,
    "Parameters": [],
    "ReturnTypes": [
      {
        "Type": "System.Collections.Generic.IEnumerable\u00601[[ApiEjemplo.Models.LoteEtapa, ApiEjemplo, Version=1.0.0.0, Culture=neutral, PublicKeyToken=null]]",
        "MediaTypes": [
          "text/plain",
          "application/json",
          "text/json"
        ],
        "StatusCode": 200
      }
    ]
  },
  {
    "ContainingType": "ApiEjemplo.Controllers.LoteEtapasController",
    "Method": "PostLoteEtapa",
    "RelativePath": "api/LoteEtapas",
    "HttpMethod": "POST",
    "IsController": true,
    "Order": 0,
    "Parameters": [
      {
        "Name": "loteEtapa",
        "Type": "ApiEjemplo.Models.LoteEtapa",
        "IsRequired": true
      }
    ],
    "ReturnTypes": [
      {
        "Type": "ApiEjemplo.Models.LoteEtapa",
        "MediaTypes": [
          "text/plain",
          "application/json",
          "text/json"
        ],
        "StatusCode": 200
      }
    ]
  },
  {
    "ContainingType": "ApiEjemplo.Controllers.LoteEtapasController",
    "Method": "GetLoteEtapa",
    "RelativePath": "api/LoteEtapas/{id}",
    "HttpMethod": "GET",
    "IsController": true,
    "Order": 0,
    "Parameters": [
      {
        "Name": "id",
        "Type": "System.Int32",
        "IsRequired": true
      }
    ],
    "ReturnTypes": [
      {
        "Type": "ApiEjemplo.Models.LoteEtapa",
        "MediaTypes": [
          "text/plain",
          "application/json",
          "text/json"
        ],
        "StatusCode": 200
      }
    ]
  },
  {
    "ContainingType": "ApiEjemplo.Controllers.LoteEtapasController",
    "Method": "PutLoteEtapa",
    "RelativePath": "api/LoteEtapas/{id}",
    "HttpMethod": "PUT",
    "IsController": true,
    "Order": 0,
    "Parameters": [
      {
        "Name": "id",
        "Type": "System.Int32",
        "IsRequired": true
      },
      {
        "Name": "loteEtapa",
        "Type": "ApiEjemplo.Models.LoteEtapa",
        "IsRequired": true
      }
    ],
    "ReturnTypes": []
  },
  {
    "ContainingType": "ApiEjemplo.Controllers.LoteEtapasController",
    "Method": "DeleteLoteEtapa",
    "RelativePath": "api/LoteEtapas/{id}",
    "HttpMethod": "DELETE",
    "IsController": true,
    "Order": 0,
    "Parameters": [
      {
        "Name": "id",
        "Type": "System.Int32",
        "IsRequired": true
      }
    ],
    "ReturnTypes": []
  },
  {
    "ContainingType": "ApiEjemplo.Controllers.LotesController",
    "Method": "GetLotes",
    "RelativePath": "api/Lotes",
    "HttpMethod": "GET",
    "IsController": true,
    "Order": 0,
    "Parameters": [],
    "ReturnTypes": [
      {
        "Type": "System.Collections.Generic.IEnumerable\u00601[[ApiEjemplo.Models.Lotes, ApiEjemplo, Version=1.0.0.0, Culture=neutral, PublicKeyToken=null]]",
        "MediaTypes": [
          "text/plain",
          "application/json",
          "text/json"
        ],
        "StatusCode": 200
      }
    ]
  },
  {
    "ContainingType": "ApiEjemplo.Controllers.LotesController",
    "Method": "PostLotes",
    "RelativePath": "api/Lotes",
    "HttpMethod": "POST",
    "IsController": true,
    "Order": 0,
    "Parameters": [
      {
        "Name": "lotes",
        "Type": "ApiEjemplo.Models.Lotes",
        "IsRequired": true
      }
    ],
    "ReturnTypes": [
      {
        "Type": "ApiEjemplo.Models.Lotes",
        "MediaTypes": [
          "text/plain",
          "application/json",
          "text/json"
        ],
        "StatusCode": 200
      }
    ]
  },
  {
    "ContainingType": "ApiEjemplo.Controllers.LotesController",
    "Method": "GetLotes",
    "RelativePath": "api/Lotes/{id}",
    "HttpMethod": "GET",
    "IsController": true,
    "Order": 0,
    "Parameters": [
      {
        "Name": "id",
        "Type": "System.Int32",
        "IsRequired": true
      }
    ],
    "ReturnTypes": [
      {
        "Type": "ApiEjemplo.Models.Lotes",
        "MediaTypes": [
          "text/plain",
          "application/json",
          "text/json"
        ],
        "StatusCode": 200
      }
    ]
  },
  {
    "ContainingType": "ApiEjemplo.Controllers.LotesController",
    "Method": "PutLotes",
    "RelativePath": "api/Lotes/{id}",
    "HttpMethod": "PUT",
    "IsController": true,
    "Order": 0,
    "Parameters": [
      {
        "Name": "id",
        "Type": "System.Int32",
        "IsRequired": true
      },
      {
        "Name": "lotes",
        "Type": "ApiEjemplo.Models.Lotes",
        "IsRequired": true
      }
    ],
    "ReturnTypes": []
  },
  {
    "ContainingType": "ApiEjemplo.Controllers.LotesController",
    "Method": "DeleteLotes",
    "RelativePath": "api/Lotes/{id}",
    "HttpMethod": "DELETE",
    "IsController": true,
    "Order": 0,
    "Parameters": [
      {
        "Name": "id",
        "Type": "System.Int32",
        "IsRequired": true
      }
    ],
    "ReturnTypes": []
  },
  {
    "ContainingType": "ApiEjemplo.Controllers.LotesTerminadosController",
    "Method": "GetLotesTerminados",
    "RelativePath": "api/LotesTerminados",
    "HttpMethod": "GET",
    "IsController": true,
    "Order": 0,
    "Parameters": [],
    "ReturnTypes": [
      {
        "Type": "System.Collections.Generic.IEnumerable\u00601[[ApiEjemplo.Models.LotesTerminados, ApiEjemplo, Version=1.0.0.0, Culture=neutral, PublicKeyToken=null]]",
        "MediaTypes": [
          "text/plain",
          "application/json",
          "text/json"
        ],
        "StatusCode": 200
      }
    ]
  },
  {
    "ContainingType": "ApiEjemplo.Controllers.LotesTerminadosController",
    "Method": "PostLotesTerminados",
    "RelativePath": "api/LotesTerminados",
    "HttpMethod": "POST",
    "IsController": true,
    "Order": 0,
    "Parameters": [
      {
        "Name": "lotesTerminados",
        "Type": "ApiEjemplo.Models.LotesTerminados",
        "IsRequired": true
      }
    ],
    "ReturnTypes": [
      {
        "Type": "ApiEjemplo.Models.LotesTerminados",
        "MediaTypes": [
          "text/plain",
          "application/json",
          "text/json"
        ],
        "StatusCode": 200
      }
    ]
  },
  {
    "ContainingType": "ApiEjemplo.Controllers.LotesTerminadosController",
    "Method": "GetLotesTerminados",
    "RelativePath": "api/LotesTerminados/{id}",
    "HttpMethod": "GET",
    "IsController": true,
    "Order": 0,
    "Parameters": [
      {
        "Name": "id",
        "Type": "System.Int32",
        "IsRequired": true
      }
    ],
    "ReturnTypes": [
      {
        "Type": "ApiEjemplo.Models.LotesTerminados",
        "MediaTypes": [
          "text/plain",
          "application/json",
          "text/json"
        ],
        "StatusCode": 200
      }
    ]
  },
  {
    "ContainingType": "ApiEjemplo.Controllers.LotesTerminadosController",
    "Method": "PutLotesTerminados",
    "RelativePath": "api/LotesTerminados/{id}",
    "HttpMethod": "PUT",
    "IsController": true,
    "Order": 0,
    "Parameters": [
      {
        "Name": "id",
        "Type": "System.Int32",
        "IsRequired": true
      },
      {
        "Name": "lotesTerminados",
        "Type": "ApiEjemplo.Models.LotesTerminados",
        "IsRequired": true
      }
    ],
    "ReturnTypes": []
  },
  {
    "ContainingType": "ApiEjemplo.Controllers.LotesTerminadosController",
    "Method": "DeleteLotesTerminados",
    "RelativePath": "api/LotesTerminados/{id}",
    "HttpMethod": "DELETE",
    "IsController": true,
    "Order": 0,
    "Parameters": [
      {
        "Name": "id",
        "Type": "System.Int32",
        "IsRequired": true
      }
    ],
    "ReturnTypes": []
  },
  {
    "ContainingType": "ApiEjemplo.Controllers.OrdenCompraTipoGranoLotesController",
    "Method": "GetOrdenCompraTipoGranoLotes",
    "RelativePath": "api/OrdenCompraTipoGranoLotes",
    "HttpMethod": "GET",
    "IsController": true,
    "Order": 0,
    "Parameters": [],
    "ReturnTypes": [
      {
        "Type": "System.Collections.Generic.IEnumerable\u00601[[ApiEjemplo.Models.OrdenCompraTipoGranoLote, ApiEjemplo, Version=1.0.0.0, Culture=neutral, PublicKeyToken=null]]",
        "MediaTypes": [
          "text/plain",
          "application/json",
          "text/json"
        ],
        "StatusCode": 200
      }
    ]
  },
  {
    "ContainingType": "ApiEjemplo.Controllers.OrdenCompraTipoGranoLotesController",
    "Method": "PostOrdenCompraTipoGranoLote",
    "RelativePath": "api/OrdenCompraTipoGranoLotes",
    "HttpMethod": "POST",
    "IsController": true,
    "Order": 0,
    "Parameters": [
      {
        "Name": "ordenCompraTipoGranoLote",
        "Type": "ApiEjemplo.Models.OrdenCompraTipoGranoLote",
        "IsRequired": true
      }
    ],
    "ReturnTypes": [
      {
        "Type": "ApiEjemplo.Models.OrdenCompraTipoGranoLote",
        "MediaTypes": [
          "text/plain",
          "application/json",
          "text/json"
        ],
        "StatusCode": 200
      }
    ]
  },
  {
    "ContainingType": "ApiEjemplo.Controllers.OrdenCompraTipoGranoLotesController",
    "Method": "GetOrdenCompraTipoGranoLote",
    "RelativePath": "api/OrdenCompraTipoGranoLotes/{id}",
    "HttpMethod": "GET",
    "IsController": true,
    "Order": 0,
    "Parameters": [
      {
        "Name": "id",
        "Type": "System.Int32",
        "IsRequired": true
      }
    ],
    "ReturnTypes": [
      {
        "Type": "ApiEjemplo.Models.OrdenCompraTipoGranoLote",
        "MediaTypes": [
          "text/plain",
          "application/json",
          "text/json"
        ],
        "StatusCode": 200
      }
    ]
  },
  {
    "ContainingType": "ApiEjemplo.Controllers.OrdenCompraTipoGranoLotesController",
    "Method": "PutOrdenCompraTipoGranoLote",
    "RelativePath": "api/OrdenCompraTipoGranoLotes/{id}",
    "HttpMethod": "PUT",
    "IsController": true,
    "Order": 0,
    "Parameters": [
      {
        "Name": "id",
        "Type": "System.Int32",
        "IsRequired": true
      },
      {
        "Name": "ordenCompraTipoGranoLote",
        "Type": "ApiEjemplo.Models.OrdenCompraTipoGranoLote",
        "IsRequired": true
      }
    ],
    "ReturnTypes": []
  },
  {
    "ContainingType": "ApiEjemplo.Controllers.OrdenCompraTipoGranoLotesController",
    "Method": "DeleteOrdenCompraTipoGranoLote",
    "RelativePath": "api/OrdenCompraTipoGranoLotes/{id}",
    "HttpMethod": "DELETE",
    "IsController": true,
    "Order": 0,
    "Parameters": [
      {
        "Name": "id",
        "Type": "System.Int32",
        "IsRequired": true
      }
    ],
    "ReturnTypes": []
  },
  {
    "ContainingType": "ApiEjemplo.Controllers.OrdenCompraTipoGranosController",
    "Method": "GetOrdenCompraTipoGranos",
    "RelativePath": "api/OrdenCompraTipoGranos",
    "HttpMethod": "GET",
    "IsController": true,
    "Order": 0,
    "Parameters": [],
    "ReturnTypes": [
      {
        "Type": "System.Collections.Generic.IEnumerable\u00601[[ApiEjemplo.Models.OrdenCompraTipoGrano, ApiEjemplo, Version=1.0.0.0, Culture=neutral, PublicKeyToken=null]]",
        "MediaTypes": [
          "text/plain",
          "application/json",
          "text/json"
        ],
        "StatusCode": 200
      }
    ]
  },
  {
    "ContainingType": "ApiEjemplo.Controllers.OrdenCompraTipoGranosController",
    "Method": "PostOrdenCompraTipoGrano",
    "RelativePath": "api/OrdenCompraTipoGranos",
    "HttpMethod": "POST",
    "IsController": true,
    "Order": 0,
    "Parameters": [
      {
        "Name": "ordenCompraTipoGrano",
        "Type": "ApiEjemplo.Models.OrdenCompraTipoGrano",
        "IsRequired": true
      }
    ],
    "ReturnTypes": [
      {
        "Type": "ApiEjemplo.Models.OrdenCompraTipoGrano",
        "MediaTypes": [
          "text/plain",
          "application/json",
          "text/json"
        ],
        "StatusCode": 200
      }
    ]
  },
  {
    "ContainingType": "ApiEjemplo.Controllers.OrdenCompraTipoGranosController",
    "Method": "GetOrdenCompraTipoGrano",
    "RelativePath": "api/OrdenCompraTipoGranos/{id}",
    "HttpMethod": "GET",
    "IsController": true,
    "Order": 0,
    "Parameters": [
      {
        "Name": "id",
        "Type": "System.Int32",
        "IsRequired": true
      }
    ],
    "ReturnTypes": [
      {
        "Type": "ApiEjemplo.Models.OrdenCompraTipoGrano",
        "MediaTypes": [
          "text/plain",
          "application/json",
          "text/json"
        ],
        "StatusCode": 200
      }
    ]
  },
  {
    "ContainingType": "ApiEjemplo.Controllers.OrdenCompraTipoGranosController",
    "Method": "PutOrdenCompraTipoGrano",
    "RelativePath": "api/OrdenCompraTipoGranos/{id}",
    "HttpMethod": "PUT",
    "IsController": true,
    "Order": 0,
    "Parameters": [
      {
        "Name": "id",
        "Type": "System.Int32",
        "IsRequired": true
      },
      {
        "Name": "ordenCompraTipoGrano",
        "Type": "ApiEjemplo.Models.OrdenCompraTipoGrano",
        "IsRequired": true
      }
    ],
    "ReturnTypes": []
  },
  {
    "ContainingType": "ApiEjemplo.Controllers.OrdenCompraTipoGranosController",
    "Method": "DeleteOrdenCompraTipoGrano",
    "RelativePath": "api/OrdenCompraTipoGranos/{id}",
    "HttpMethod": "DELETE",
    "IsController": true,
    "Order": 0,
    "Parameters": [
      {
        "Name": "id",
        "Type": "System.Int32",
        "IsRequired": true
      }
    ],
    "ReturnTypes": []
  },
  {
    "ContainingType": "ApiEjemplo.Controllers.OrdenesComprasController",
    "Method": "GetOrdenesCompras",
    "RelativePath": "api/OrdenesCompras",
    "HttpMethod": "GET",
    "IsController": true,
    "Order": 0,
    "Parameters": [],
    "ReturnTypes": [
      {
        "Type": "System.Collections.Generic.IEnumerable\u00601[[ApiEjemplo.Models.OrdenesCompra, ApiEjemplo, Version=1.0.0.0, Culture=neutral, PublicKeyToken=null]]",
        "MediaTypes": [
          "text/plain",
          "application/json",
          "text/json"
        ],
        "StatusCode": 200
      }
    ]
  },
  {
    "ContainingType": "ApiEjemplo.Controllers.OrdenesComprasController",
    "Method": "PostOrdenesCompra",
    "RelativePath": "api/OrdenesCompras",
    "HttpMethod": "POST",
    "IsController": true,
    "Order": 0,
    "Parameters": [
      {
        "Name": "ordenesCompra",
        "Type": "ApiEjemplo.Models.OrdenesCompra",
        "IsRequired": true
      }
    ],
    "ReturnTypes": [
      {
        "Type": "ApiEjemplo.Models.OrdenesCompra",
        "MediaTypes": [
          "text/plain",
          "application/json",
          "text/json"
        ],
        "StatusCode": 200
      }
    ]
  },
  {
    "ContainingType": "ApiEjemplo.Controllers.OrdenesComprasController",
    "Method": "GetOrdenesCompra",
    "RelativePath": "api/OrdenesCompras/{id}",
    "HttpMethod": "GET",
    "IsController": true,
    "Order": 0,
    "Parameters": [
      {
        "Name": "id",
        "Type": "System.Int32",
        "IsRequired": true
      }
    ],
    "ReturnTypes": [
      {
        "Type": "ApiEjemplo.Models.OrdenesCompra",
        "MediaTypes": [
          "text/plain",
          "application/json",
          "text/json"
        ],
        "StatusCode": 200
      }
    ]
  },
  {
    "ContainingType": "ApiEjemplo.Controllers.OrdenesComprasController",
    "Method": "PutOrdenesCompra",
    "RelativePath": "api/OrdenesCompras/{id}",
    "HttpMethod": "PUT",
    "IsController": true,
    "Order": 0,
    "Parameters": [
      {
        "Name": "id",
        "Type": "System.Int32",
        "IsRequired": true
      },
      {
        "Name": "ordenesCompra",
        "Type": "ApiEjemplo.Models.OrdenesCompra",
        "IsRequired": true
      }
    ],
    "ReturnTypes": []
  },
  {
    "ContainingType": "ApiEjemplo.Controllers.OrdenesComprasController",
    "Method": "DeleteOrdenesCompra",
    "RelativePath": "api/OrdenesCompras/{id}",
    "HttpMethod": "DELETE",
    "IsController": true,
    "Order": 0,
    "Parameters": [
      {
        "Name": "id",
        "Type": "System.Int32",
        "IsRequired": true
      }
    ],
    "ReturnTypes": []
  },
  {
    "ContainingType": "ApiEjemplo.Controllers.PedidoLoteTerminadosController",
    "Method": "GetPedidoLoteTerminados",
    "RelativePath": "api/PedidoLoteTerminados",
    "HttpMethod": "GET",
    "IsController": true,
    "Order": 0,
    "Parameters": [],
    "ReturnTypes": [
      {
        "Type": "System.Collections.Generic.IEnumerable\u00601[[ApiEjemplo.Models.PedidoLoteTerminado, ApiEjemplo, Version=1.0.0.0, Culture=neutral, PublicKeyToken=null]]",
        "MediaTypes": [
          "text/plain",
          "application/json",
          "text/json"
        ],
        "StatusCode": 200
      }
    ]
  },
  {
    "ContainingType": "ApiEjemplo.Controllers.PedidoLoteTerminadosController",
    "Method": "PostPedidoLoteTerminado",
    "RelativePath": "api/PedidoLoteTerminados",
    "HttpMethod": "POST",
    "IsController": true,
    "Order": 0,
    "Parameters": [
      {
        "Name": "pedidoLoteTerminado",
        "Type": "ApiEjemplo.Models.PedidoLoteTerminado",
        "IsRequired": true
      }
    ],
    "ReturnTypes": [
      {
        "Type": "ApiEjemplo.Models.PedidoLoteTerminado",
        "MediaTypes": [
          "text/plain",
          "application/json",
          "text/json"
        ],
        "StatusCode": 200
      }
    ]
  },
  {
    "ContainingType": "ApiEjemplo.Controllers.PedidoLoteTerminadosController",
    "Method": "GetPedidoLoteTerminado",
    "RelativePath": "api/PedidoLoteTerminados/{id}",
    "HttpMethod": "GET",
    "IsController": true,
    "Order": 0,
    "Parameters": [
      {
        "Name": "id",
        "Type": "System.Int32",
        "IsRequired": true
      }
    ],
    "ReturnTypes": [
      {
        "Type": "ApiEjemplo.Models.PedidoLoteTerminado",
        "MediaTypes": [
          "text/plain",
          "application/json",
          "text/json"
        ],
        "StatusCode": 200
      }
    ]
  },
  {
    "ContainingType": "ApiEjemplo.Controllers.PedidoLoteTerminadosController",
    "Method": "PutPedidoLoteTerminado",
    "RelativePath": "api/PedidoLoteTerminados/{id}",
    "HttpMethod": "PUT",
    "IsController": true,
    "Order": 0,
    "Parameters": [
      {
        "Name": "id",
        "Type": "System.Int32",
        "IsRequired": true
      },
      {
        "Name": "pedidoLoteTerminado",
        "Type": "ApiEjemplo.Models.PedidoLoteTerminado",
        "IsRequired": true
      }
    ],
    "ReturnTypes": []
  },
  {
    "ContainingType": "ApiEjemplo.Controllers.PedidoLoteTerminadosController",
    "Method": "DeletePedidoLoteTerminado",
    "RelativePath": "api/PedidoLoteTerminados/{id}",
    "HttpMethod": "DELETE",
    "IsController": true,
    "Order": 0,
    "Parameters": [
      {
        "Name": "id",
        "Type": "System.Int32",
        "IsRequired": true
      }
    ],
    "ReturnTypes": []
  },
  {
    "ContainingType": "ApiEjemplo.Controllers.PedidoRutasController",
    "Method": "GetPedidoRutas",
    "RelativePath": "api/PedidoRutas",
    "HttpMethod": "GET",
    "IsController": true,
    "Order": 0,
    "Parameters": [],
    "ReturnTypes": [
      {
        "Type": "System.Collections.Generic.IEnumerable\u00601[[ApiEjemplo.Models.PedidoRuta, ApiEjemplo, Version=1.0.0.0, Culture=neutral, PublicKeyToken=null]]",
        "MediaTypes": [
          "text/plain",
          "application/json",
          "text/json"
        ],
        "StatusCode": 200
      }
    ]
  },
  {
    "ContainingType": "ApiEjemplo.Controllers.PedidoRutasController",
    "Method": "PostPedidoRuta",
    "RelativePath": "api/PedidoRutas",
    "HttpMethod": "POST",
    "IsController": true,
    "Order": 0,
    "Parameters": [
      {
        "Name": "pedidoRuta",
        "Type": "ApiEjemplo.Models.PedidoRuta",
        "IsRequired": true
      }
    ],
    "ReturnTypes": [
      {
        "Type": "ApiEjemplo.Models.PedidoRuta",
        "MediaTypes": [
          "text/plain",
          "application/json",
          "text/json"
        ],
        "StatusCode": 200
      }
    ]
  },
  {
    "ContainingType": "ApiEjemplo.Controllers.PedidoRutasController",
    "Method": "GetPedidoRuta",
    "RelativePath": "api/PedidoRutas/{id}",
    "HttpMethod": "GET",
    "IsController": true,
    "Order": 0,
    "Parameters": [
      {
        "Name": "id",
        "Type": "System.Int32",
        "IsRequired": true
      }
    ],
    "ReturnTypes": [
      {
        "Type": "ApiEjemplo.Models.PedidoRuta",
        "MediaTypes": [
          "text/plain",
          "application/json",
          "text/json"
        ],
        "StatusCode": 200
      }
    ]
  },
  {
    "ContainingType": "ApiEjemplo.Controllers.PedidoRutasController",
    "Method": "PutPedidoRuta",
    "RelativePath": "api/PedidoRutas/{id}",
    "HttpMethod": "PUT",
    "IsController": true,
    "Order": 0,
    "Parameters": [
      {
        "Name": "id",
        "Type": "System.Int32",
        "IsRequired": true
      },
      {
        "Name": "pedidoRuta",
        "Type": "ApiEjemplo.Models.PedidoRuta",
        "IsRequired": true
      }
    ],
    "ReturnTypes": []
  },
  {
    "ContainingType": "ApiEjemplo.Controllers.PedidoRutasController",
    "Method": "DeletePedidoRuta",
    "RelativePath": "api/PedidoRutas/{id}",
    "HttpMethod": "DELETE",
    "IsController": true,
    "Order": 0,
    "Parameters": [
      {
        "Name": "id",
        "Type": "System.Int32",
        "IsRequired": true
      }
    ],
    "ReturnTypes": []
  },
  {
    "ContainingType": "ApiEjemplo.Controllers.PedidosController",
    "Method": "GetPedidos",
    "RelativePath": "api/Pedidos",
    "HttpMethod": "GET",
    "IsController": true,
    "Order": 0,
    "Parameters": [],
    "ReturnTypes": [
      {
        "Type": "System.Collections.Generic.IEnumerable\u00601[[ApiEjemplo.Models.Pedidos, ApiEjemplo, Version=1.0.0.0, Culture=neutral, PublicKeyToken=null]]",
        "MediaTypes": [
          "text/plain",
          "application/json",
          "text/json"
        ],
        "StatusCode": 200
      }
    ]
  },
  {
    "ContainingType": "ApiEjemplo.Controllers.PedidosController",
    "Method": "PostPedidos",
    "RelativePath": "api/Pedidos",
    "HttpMethod": "POST",
    "IsController": true,
    "Order": 0,
    "Parameters": [
      {
        "Name": "pedidos",
        "Type": "ApiEjemplo.Models.Pedidos",
        "IsRequired": true
      }
    ],
    "ReturnTypes": [
      {
        "Type": "ApiEjemplo.Models.Pedidos",
        "MediaTypes": [
          "text/plain",
          "application/json",
          "text/json"
        ],
        "StatusCode": 200
      }
    ]
  },
  {
    "ContainingType": "ApiEjemplo.Controllers.PedidosController",
    "Method": "GetPedidos",
    "RelativePath": "api/Pedidos/{id}",
    "HttpMethod": "GET",
    "IsController": true,
    "Order": 0,
    "Parameters": [
      {
        "Name": "id",
        "Type": "System.Int32",
        "IsRequired": true
      }
    ],
    "ReturnTypes": [
      {
        "Type": "ApiEjemplo.Models.Pedidos",
        "MediaTypes": [
          "text/plain",
          "application/json",
          "text/json"
        ],
        "StatusCode": 200
      }
    ]
  },
  {
    "ContainingType": "ApiEjemplo.Controllers.PedidosController",
    "Method": "PutPedidos",
    "RelativePath": "api/Pedidos/{id}",
    "HttpMethod": "PUT",
    "IsController": true,
    "Order": 0,
    "Parameters": [
      {
        "Name": "id",
        "Type": "System.Int32",
        "IsRequired": true
      },
      {
        "Name": "pedidos",
        "Type": "ApiEjemplo.Models.Pedidos",
        "IsRequired": true
      }
    ],
    "ReturnTypes": []
  },
  {
    "ContainingType": "ApiEjemplo.Controllers.PedidosController",
    "Method": "DeletePedidos",
    "RelativePath": "api/Pedidos/{id}",
    "HttpMethod": "DELETE",
    "IsController": true,
    "Order": 0,
    "Parameters": [
      {
        "Name": "id",
        "Type": "System.Int32",
        "IsRequired": true
      }
    ],
    "ReturnTypes": []
  },
  {
    "ContainingType": "ApiEjemplo.Controllers.PresentacionesController",
    "Method": "GetPresentaciones",
    "RelativePath": "api/Presentaciones",
    "HttpMethod": "GET",
    "IsController": true,
    "Order": 0,
    "Parameters": [],
    "ReturnTypes": [
      {
        "Type": "System.Collections.Generic.IEnumerable\u00601[[ApiEjemplo.Models.Presentaciones, ApiEjemplo, Version=1.0.0.0, Culture=neutral, PublicKeyToken=null]]",
        "MediaTypes": [
          "text/plain",
          "application/json",
          "text/json"
        ],
        "StatusCode": 200
      }
    ]
  },
  {
    "ContainingType": "ApiEjemplo.Controllers.PresentacionesController",
    "Method": "PostPresentaciones",
    "RelativePath": "api/Presentaciones",
    "HttpMethod": "POST",
    "IsController": true,
    "Order": 0,
    "Parameters": [
      {
        "Name": "presentaciones",
        "Type": "ApiEjemplo.Models.Presentaciones",
        "IsRequired": true
      }
    ],
    "ReturnTypes": [
      {
        "Type": "ApiEjemplo.Models.Presentaciones",
        "MediaTypes": [
          "text/plain",
          "application/json",
          "text/json"
        ],
        "StatusCode": 200
      }
    ]
  },
  {
    "ContainingType": "ApiEjemplo.Controllers.PresentacionesController",
    "Method": "GetPresentaciones",
    "RelativePath": "api/Presentaciones/{id}",
    "HttpMethod": "GET",
    "IsController": true,
    "Order": 0,
    "Parameters": [
      {
        "Name": "id",
        "Type": "System.Int32",
        "IsRequired": true
      }
    ],
    "ReturnTypes": [
      {
        "Type": "ApiEjemplo.Models.Presentaciones",
        "MediaTypes": [
          "text/plain",
          "application/json",
          "text/json"
        ],
        "StatusCode": 200
      }
    ]
  },
  {
    "ContainingType": "ApiEjemplo.Controllers.PresentacionesController",
    "Method": "PutPresentaciones",
    "RelativePath": "api/Presentaciones/{id}",
    "HttpMethod": "PUT",
    "IsController": true,
    "Order": 0,
    "Parameters": [
      {
        "Name": "id",
        "Type": "System.Int32",
        "IsRequired": true
      },
      {
        "Name": "presentaciones",
        "Type": "ApiEjemplo.Models.Presentaciones",
        "IsRequired": true
      }
    ],
    "ReturnTypes": []
  },
  {
    "ContainingType": "ApiEjemplo.Controllers.PresentacionesController",
    "Method": "DeletePresentaciones",
    "RelativePath": "api/Presentaciones/{id}",
    "HttpMethod": "DELETE",
    "IsController": true,
    "Order": 0,
    "Parameters": [
      {
        "Name": "id",
        "Type": "System.Int32",
        "IsRequired": true
      }
    ],
    "ReturnTypes": []
  },
  {
    "ContainingType": "ApiEjemplo.Controllers.ProductosController",
    "Method": "GetProductos",
    "RelativePath": "api/Productos",
    "HttpMethod": "GET",
    "IsController": true,
    "Order": 0,
    "Parameters": [],
    "ReturnTypes": [
      {
        "Type": "System.Collections.Generic.IEnumerable\u00601[[ApiEjemplo.Models.Productos, ApiEjemplo, Version=1.0.0.0, Culture=neutral, PublicKeyToken=null]]",
        "MediaTypes": [
          "text/plain",
          "application/json",
          "text/json"
        ],
        "StatusCode": 200
      }
    ]
  },
  {
    "ContainingType": "ApiEjemplo.Controllers.ProductosController",
    "Method": "PostProductos",
    "RelativePath": "api/Productos",
    "HttpMethod": "POST",
    "IsController": true,
    "Order": 0,
    "Parameters": [
      {
        "Name": "productos",
        "Type": "ApiEjemplo.Models.Productos",
        "IsRequired": true
      }
    ],
    "ReturnTypes": [
      {
        "Type": "ApiEjemplo.Models.Productos",
        "MediaTypes": [
          "text/plain",
          "application/json",
          "text/json"
        ],
        "StatusCode": 200
      }
    ]
  },
  {
    "ContainingType": "ApiEjemplo.Controllers.ProductosController",
    "Method": "GetProductos",
    "RelativePath": "api/Productos/{id}",
    "HttpMethod": "GET",
    "IsController": true,
    "Order": 0,
    "Parameters": [
      {
        "Name": "id",
        "Type": "System.Int32",
        "IsRequired": true
      }
    ],
    "ReturnTypes": [
      {
        "Type": "ApiEjemplo.Models.Productos",
        "MediaTypes": [
          "text/plain",
          "application/json",
          "text/json"
        ],
        "StatusCode": 200
      }
    ]
  },
  {
    "ContainingType": "ApiEjemplo.Controllers.ProductosController",
    "Method": "PutProductos",
    "RelativePath": "api/Productos/{id}",
    "HttpMethod": "PUT",
    "IsController": true,
    "Order": 0,
    "Parameters": [
      {
        "Name": "id",
        "Type": "System.Int32",
        "IsRequired": true
      },
      {
        "Name": "productos",
        "Type": "ApiEjemplo.Models.Productos",
        "IsRequired": true
      }
    ],
    "ReturnTypes": []
  },
  {
    "ContainingType": "ApiEjemplo.Controllers.ProductosController",
    "Method": "DeleteProductos",
    "RelativePath": "api/Productos/{id}",
    "HttpMethod": "DELETE",
    "IsController": true,
    "Order": 0,
    "Parameters": [
      {
        "Name": "id",
        "Type": "System.Int32",
        "IsRequired": true
      }
    ],
    "ReturnTypes": []
  },
  {
    "ContainingType": "ApiEjemplo.Controllers.RutasController",
    "Method": "GetRutas",
    "RelativePath": "api/Rutas",
    "HttpMethod": "GET",
    "IsController": true,
    "Order": 0,
    "Parameters": [],
    "ReturnTypes": [
      {
        "Type": "System.Collections.Generic.IEnumerable\u00601[[ApiEjemplo.Models.Rutas, ApiEjemplo, Version=1.0.0.0, Culture=neutral, PublicKeyToken=null]]",
        "MediaTypes": [
          "text/plain",
          "application/json",
          "text/json"
        ],
        "StatusCode": 200
      }
    ]
  },
  {
    "ContainingType": "ApiEjemplo.Controllers.RutasController",
    "Method": "PostRutas",
    "RelativePath": "api/Rutas",
    "HttpMethod": "POST",
    "IsController": true,
    "Order": 0,
    "Parameters": [
      {
        "Name": "rutas",
        "Type": "ApiEjemplo.Models.Rutas",
        "IsRequired": true
      }
    ],
    "ReturnTypes": [
      {
        "Type": "ApiEjemplo.Models.Rutas",
        "MediaTypes": [
          "text/plain",
          "application/json",
          "text/json"
        ],
        "StatusCode": 200
      }
    ]
  },
  {
    "ContainingType": "ApiEjemplo.Controllers.RutasController",
    "Method": "GetRutas",
    "RelativePath": "api/Rutas/{id}",
    "HttpMethod": "GET",
    "IsController": true,
    "Order": 0,
    "Parameters": [
      {
        "Name": "id",
        "Type": "System.Int32",
        "IsRequired": true
      }
    ],
    "ReturnTypes": [
      {
        "Type": "ApiEjemplo.Models.Rutas",
        "MediaTypes": [
          "text/plain",
          "application/json",
          "text/json"
        ],
        "StatusCode": 200
      }
    ]
  },
  {
    "ContainingType": "ApiEjemplo.Controllers.RutasController",
    "Method": "PutRutas",
    "RelativePath": "api/Rutas/{id}",
    "HttpMethod": "PUT",
    "IsController": true,
    "Order": 0,
    "Parameters": [
      {
        "Name": "id",
        "Type": "System.Int32",
        "IsRequired": true
      },
      {
        "Name": "rutas",
        "Type": "ApiEjemplo.Models.Rutas",
        "IsRequired": true
      }
    ],
    "ReturnTypes": []
  },
  {
    "ContainingType": "ApiEjemplo.Controllers.RutasController",
    "Method": "DeleteRutas",
    "RelativePath": "api/Rutas/{id}",
    "HttpMethod": "DELETE",
    "IsController": true,
    "Order": 0,
    "Parameters": [
      {
        "Name": "id",
        "Type": "System.Int32",
        "IsRequired": true
      }
    ],
    "ReturnTypes": []
  },
  {
    "ContainingType": "ApiEjemplo.Controllers.TiposGranoesController",
    "Method": "GetTiposGranos",
    "RelativePath": "api/TiposGranoes",
    "HttpMethod": "GET",
    "IsController": true,
    "Order": 0,
    "Parameters": [],
    "ReturnTypes": [
      {
        "Type": "System.Collections.Generic.IEnumerable\u00601[[ApiEjemplo.Models.TiposGrano, ApiEjemplo, Version=1.0.0.0, Culture=neutral, PublicKeyToken=null]]",
        "MediaTypes": [
          "text/plain",
          "application/json",
          "text/json"
        ],
        "StatusCode": 200
      }
    ]
  },
  {
    "ContainingType": "ApiEjemplo.Controllers.TiposGranoesController",
    "Method": "PostTiposGrano",
    "RelativePath": "api/TiposGranoes",
    "HttpMethod": "POST",
    "IsController": true,
    "Order": 0,
    "Parameters": [
      {
        "Name": "tiposGrano",
        "Type": "ApiEjemplo.Models.TiposGrano",
        "IsRequired": true
      }
    ],
    "ReturnTypes": [
      {
        "Type": "ApiEjemplo.Models.TiposGrano",
        "MediaTypes": [
          "text/plain",
          "application/json",
          "text/json"
        ],
        "StatusCode": 200
      }
    ]
  },
  {
    "ContainingType": "ApiEjemplo.Controllers.TiposGranoesController",
    "Method": "GetTiposGrano",
    "RelativePath": "api/TiposGranoes/{id}",
    "HttpMethod": "GET",
    "IsController": true,
    "Order": 0,
    "Parameters": [
      {
        "Name": "id",
        "Type": "System.Int32",
        "IsRequired": true
      }
    ],
    "ReturnTypes": [
      {
        "Type": "ApiEjemplo.Models.TiposGrano",
        "MediaTypes": [
          "text/plain",
          "application/json",
          "text/json"
        ],
        "StatusCode": 200
      }
    ]
  },
  {
    "ContainingType": "ApiEjemplo.Controllers.TiposGranoesController",
    "Method": "PutTiposGrano",
    "RelativePath": "api/TiposGranoes/{id}",
    "HttpMethod": "PUT",
    "IsController": true,
    "Order": 0,
    "Parameters": [
      {
        "Name": "id",
        "Type": "System.Int32",
        "IsRequired": true
      },
      {
        "Name": "tiposGrano",
        "Type": "ApiEjemplo.Models.TiposGrano",
        "IsRequired": true
      }
    ],
    "ReturnTypes": []
  },
  {
    "ContainingType": "ApiEjemplo.Controllers.TiposGranoesController",
    "Method": "DeleteTiposGrano",
    "RelativePath": "api/TiposGranoes/{id}",
    "HttpMethod": "DELETE",
    "IsController": true,
    "Order": 0,
    "Parameters": [
      {
        "Name": "id",
        "Type": "System.Int32",
        "IsRequired": true
      }
    ],
    "ReturnTypes": []
  },
  {
    "ContainingType": "Program\u002B\u003C\u003Ec__DisplayClass0_0",
    "Method": "\u003C\u003CMain\u003E$\u003Eb__1",
    "RelativePath": "weatherforecast",
    "HttpMethod": "GET",
    "IsController": false,
    "Order": 0,
    "Parameters": [],
    "ReturnTypes": [
      {
        "Type": "WeatherForecast[]",
        "MediaTypes": [
          "application/json"
        ],
        "StatusCode": 200
      }
    ],
    "EndpointName": "GetWeatherForecast"
  }
]